{
	"nodes": [
		{
			"id": 8.486868487318052,
			"type": "waypoint",
			"x": 690,
			"y": 390
		},
		{
			"id": 2.9973775022617,
			"type": "waypoint",
			"x": 690,
			"y": 330
		},
		{
			"id": 3.64272363573628,
			"type": "waypoint",
			"x": 990,
			"y": 330
		},
		{
			"id": 6.179102977082069,
			"type": "waypoint",
			"x": 990,
			"y": 870
		},
		{
			"id": 3.262898506347769,
			"type": "waypoint",
			"x": 1110,
			"y": 570
		},
		{
			"id": 6.846885196129822,
			"type": "waypoint",
			"x": 1110,
			"y": 630
		},
		{
			"id": 4.464694702505425,
			"type": "waypoint",
			"x": 810,
			"y": 630
		},
		{
			"id": 4.836230228449539,
			"type": "waypoint",
			"x": 810,
			"y": 90
		},
		{
			"id": 5.1103433919257,
			"type": "waypoint",
			"x": 750,
			"y": 690
		},
		{
			"id": 0.4172096383164958,
			"type": "waypoint",
			"x": 750,
			"y": 390
		},
		{
			"id": 5.901426517176651,
			"type": "waypoint",
			"x": 1290,
			"y": 390
		},
		{
			"id": 1.4749467265812188,
			"type": "waypoint",
			"x": 990,
			"y": 270
		},
		{
			"id": 3.622023119129023,
			"type": "waypoint",
			"x": 1050,
			"y": 270
		},
		{
			"id": 6.6731820901541266,
			"type": "waypoint",
			"x": 1050,
			"y": 570
		},
		{
			"id": 1.4844684287235488,
			"type": "waypoint",
			"x": 510,
			"y": 570
		},
		{
			"id": 2.960742263048075,
			"type": "waypoint",
			"x": 810,
			"y": 690
		},
		{
			"id": 8.858267097209971,
			"type": "waypoint",
			"x": 1050,
			"y": 870
		},
		{
			"id": 1.918274745224695,
			"type": "waypoint",
			"x": 1290,
			"y": 630
		},
		{
			"id": 6.3427496995174915,
			"type": "waypoint",
			"x": 1290,
			"y": 570
		},
		{
			"id": 6.248783746546797,
			"type": "waypoint",
			"x": 1290,
			"y": 510
		},
		{
			"id": 9.801078178872926,
			"type": "waypoint",
			"x": 810,
			"y": 870
		},
		{
			"id": 2.279989028106433,
			"type": "waypoint",
			"x": 870,
			"y": 870
		},
		{
			"id": 8.19584342504613,
			"type": "waypoint",
			"x": 750,
			"y": 870
		},
		{
			"id": 0.3824611959051327,
			"type": "waypoint",
			"x": 510,
			"y": 630
		},
		{
			"id": 8.111593992143069,
			"type": "waypoint",
			"x": 510,
			"y": 390
		},
		{
			"id": 2.910492964207949,
			"type": "waypoint",
			"x": 510,
			"y": 450
		},
		{
			"id": 7.677426755629644,
			"type": "waypoint",
			"x": 750,
			"y": 90
		},
		{
			"id": 2.726144672853319,
			"type": "waypoint",
			"x": 510,
			"y": 330
		},
		{
			"id": 8.225404189841354,
			"type": "waypoint",
			"x": 930,
			"y": 870
		},
		{
			"id": 2.428844289572043,
			"type": "waypoint",
			"x": 990,
			"y": 90
		},
		{
			"id": 1.193979761396251,
			"type": "waypoint",
			"x": 1050,
			"y": 90
		},
		{
			"id": 1.7037376990829012,
			"type": "waypoint",
			"x": 1290,
			"y": 330
		},
		{
			"id": 4.226237131343837,
			"type": "waypoint",
			"x": 570,
			"y": 450
		},
		{
			"id": 3.5503087578487746,
			"type": "waypoint",
			"x": 1230,
			"y": 450
		},
		{
			"id": 4.079090798022458,
			"type": "waypoint",
			"x": 1290,
			"y": 450
		},
		{
			"id": 7.870177960428919,
			"type": "waypoint",
			"x": 570,
			"y": 510
		},
		{
			"id": 0.7653728114287461,
			"type": "waypoint",
			"x": 510,
			"y": 510
		},
		{
			"id": 3.8636983637011313,
			"type": "waypoint",
			"x": 1230,
			"y": 510
		},
		{
			"id": 3.436596873996538,
			"type": "waypoint",
			"x": 870,
			"y": 90
		},
		{
			"id": 3.7510719362588185,
			"type": "waypoint",
			"x": 930,
			"y": 90
		},
		{
			"id": 8.558707148319982,
			"type": "waypoint",
			"x": 930,
			"y": 150
		},
		{
			"id": 7.096948692116887,
			"type": "waypoint",
			"x": 870,
			"y": 150
		},
		{
			"id": 0.2751236117908018,
			"type": "waypoint",
			"x": 870,
			"y": 810
		},
		{
			"id": 1.7405147765275775,
			"type": "waypoint",
			"x": 930,
			"y": 810
		}
	],
	"zones": [],
	"links": [
		{
			"id": 0.06990263329965218,
			"type": "active",
			"src": 8.486868487318052,
			"dst": 2.9973775022617
		},
		{
			"id": 5.280397961166365,
			"type": "active",
			"src": 2.9973775022617,
			"dst": 3.64272363573628
		},
		{
			"id": 4.183275038763943,
			"type": "active",
			"src": 3.64272363573628,
			"dst": 6.179102977082069
		},
		{
			"id": 5.146141645922939,
			"type": "active",
			"src": 3.262898506347769,
			"dst": 6.846885196129822
		},
		{
			"id": 9.877657951589265,
			"type": "active",
			"src": 6.846885196129822,
			"dst": 4.464694702505425
		},
		{
			"id": 2.808539573866815,
			"type": "active",
			"src": 4.836230228449539,
			"dst": 4.464694702505425
		},
		{
			"id": 7.624642007531454,
			"type": "active",
			"src": 5.1103433919257,
			"dst": 0.4172096383164958
		},
		{
			"id": 3.1009675341538068,
			"type": "active",
			"src": 0.4172096383164958,
			"dst": 5.901426517176651
		},
		{
			"id": 1.7070964853499215,
			"type": "active",
			"src": 1.4749467265812188,
			"dst": 3.622023119129023
		},
		{
			"id": 8.261657143469074,
			"type": "active",
			"src": 3.622023119129023,
			"dst": 6.6731820901541266
		},
		{
			"id": 9.467471871202564,
			"type": "active",
			"src": 6.6731820901541266,
			"dst": 1.4844684287235488
		},
		{
			"id": 6.8396140195141975,
			"type": "active",
			"src": 2.960742263048075,
			"dst": 5.1103433919257
		},
		{
			"id": 5.196917461380346,
			"type": "active",
			"src": 8.858267097209971,
			"dst": 1.918274745224695
		},
		{
			"id": 6.938145862815912,
			"type": "active",
			"src": 3.262898506347769,
			"dst": 6.3427496995174915
		},
		{
			"id": 6.6886037446015205,
			"type": "active",
			"src": 9.801078178872926,
			"dst": 2.960742263048075
		},
		{
			"id": 9.994176811369657,
			"type": "active",
			"src": 8.19584342504613,
			"dst": 0.3824611959051327
		},
		{
			"id": 9.452109045973721,
			"type": "active",
			"src": 8.486868487318052,
			"dst": 8.111593992143069
		},
		{
			"id": 3.7294064379522096,
			"type": "active",
			"src": 7.677426755629644,
			"dst": 2.726144672853319
		},
		{
			"id": 9.448270057188065,
			"type": "active",
			"src": 1.4749467265812188,
			"dst": 2.428844289572043
		},
		{
			"id": 9.320431778164323,
			"type": "active",
			"src": 1.193979761396251,
			"dst": 1.7037376990829012
		},
		{
			"id": 7.452161286433858,
			"type": "active",
			"src": 4.226237131343837,
			"dst": 2.910492964207949
		},
		{
			"id": 9.201581881056809,
			"type": "active",
			"src": 3.5503087578487746,
			"dst": 4.079090798022458
		},
		{
			"id": 4.147426378067411,
			"type": "active",
			"src": 0.7653728114287461,
			"dst": 7.870177960428919
		},
		{
			"id": 0.1346127047487955,
			"type": "active",
			"src": 3.8636983637011313,
			"dst": 6.248783746546797
		},
		{
			"id": 3.4566018264194587,
			"type": "active",
			"src": 2.279989028106433,
			"dst": 0.2751236117908018
		},
		{
			"id": 9.603380795884163,
			"type": "active",
			"src": 1.7405147765275775,
			"dst": 8.225404189841354
		},
		{
			"id": 4.299232330887772,
			"type": "active",
			"src": 7.096948692116887,
			"dst": 3.436596873996538
		},
		{
			"id": 7.980825074072975,
			"type": "active",
			"src": 3.7510719362588185,
			"dst": 8.558707148319982
		}
	]
}